PyThermite.libs/libgcc_s-6d2d9dc8.so.1
PyThermite/PyThermite.cpython-314-x86_64-linux-musl.so
PyThermite/PyThermite.pyi
PyThermite/__init__.py
PyThermite/src/__init__.py
PyThermite/src/index/core/filtered_index.rs
PyThermite/src/index/core/index.rs
PyThermite/src/index/core/mod.rs
PyThermite/src/index/core/query/b_tree/composite_key.rs
PyThermite/src/index/core/query/b_tree/key.rs
PyThermite/src/index/core/query/b_tree/mod.rs
PyThermite/src/index/core/query/b_tree/nodes/internal_node.rs
PyThermite/src/index/core/query/b_tree/nodes/leaf_node.rs
PyThermite/src/index/core/query/b_tree/nodes/mod.rs
PyThermite/src/index/core/query/b_tree/ranged_b_tree.rs
PyThermite/src/index/core/query/mod.rs
PyThermite/src/index/core/query/query.rs
PyThermite/src/index/core/query/query_ops.rs
PyThermite/src/index/core/stored_item.rs
PyThermite/src/index/core/structures/centered_array/centered_array.rs
PyThermite/src/index/core/structures/centered_array/mod.rs
PyThermite/src/index/core/structures/hybrid_hashmap/hybrid_hashmap.rs
PyThermite/src/index/core/structures/hybrid_hashmap/mod.rs
PyThermite/src/index/core/structures/hybrid_hashmap/radix_map.rs
PyThermite/src/index/core/structures/hybrid_set/hybrid_set.rs
PyThermite/src/index/core/structures/hybrid_set/medium.rs
PyThermite/src/index/core/structures/hybrid_set/mod.rs
PyThermite/src/index/core/structures/hybrid_set/small.rs
PyThermite/src/index/core/structures/mod.rs
PyThermite/src/index/core/structures/shards/hashmap/hashmap.rs
PyThermite/src/index/core/structures/shards/hashmap/mod.rs
PyThermite/src/index/core/structures/shards/mod.rs
PyThermite/src/index/core/structures/string_interner/immutable_interner.rs
PyThermite/src/index/core/structures/string_interner/interner.rs
PyThermite/src/index/core/structures/string_interner/interner_view.rs
PyThermite/src/index/core/structures/string_interner/mod.rs
PyThermite/src/index/core/structures/string_interner/mutable_interner.rs
PyThermite/src/index/hybrid_hashmap.rs
pythermite-0.4.2.dist-info/METADATA
pythermite-0.4.2.dist-info/WHEEL
pythermite-0.4.2.dist-info/licenses/LICENSE
pythermite-0.4.2.dist-info/RECORD
