Metadata-Version: 2.4
Name: pythermite
Version: 0.4.2
Classifier: Programming Language :: Rust
Classifier: Programming Language :: Python :: Implementation :: CPython
Classifier: Programming Language :: Python :: Implementation :: PyPy
Requires-Dist: maturin>=1.8.6,<2.0.0
Requires-Dist: pytest>=8.4.2,<9.0.0
Requires-Dist: pip-tools ; extra == 'dev'
Provides-Extra: dev
License-File: LICENSE
Summary: Python object indexer for ETL, search for anything by anything
Keywords: index,search,storage,ETL,ELT,searchmeta
Author-email: Tyler Robbins <tylerrobbins5678@gmail.com>
Maintainer-email: Tyler Robbins <tylerrobbins5678@gmail.com>
Requires-Python: >=3.11
